src/__init__.py
src/config.py
src/debug.log
src/main.py
src/process.py
twitter_async_search-1.1.2.dist-info/METADATA
twitter_async_search-1.1.2.dist-info/WHEEL
twitter_async_search-1.1.2.dist-info/entry_points.txt
twitter_async_search-1.1.2.dist-info/top_level.txt
twitter_async_search-1.1.2.dist-info/RECORD
