Metadata-Version: 2.1
Name: twitter-async-search
Version: 1.1.2
Summary: Fast twitter search API
Home-page: https://github.com/trevorhobenshield/twitter-async-search
Author: Trevor Hobenshield
Author-email: trevorhobenshield@gmail.com
Keywords: twitter search api async
Requires-Dist: aiohttp
Requires-Dist: requests
